<?xml version="1.0" encoding="UTF-8" standalone="no"?><SimpleProgram><ChooseCommand><SimpleCases><SingleCase><EmptyCommand/><CaseLiterals><SequentialCaseRange><SequentialCaseRange><SimpleCaseRange><CaseLiteral><IntegerLiteral value="1"/></CaseLiteral></SimpleCaseRange><SimpleCaseRange><CaseLiteral><IntegerLiteral value="2"/></CaseLiteral></SimpleCaseRange></SequentialCaseRange><SimpleCaseRange><CaseLiteral><IntegerLiteral value="2"/></CaseLiteral></SimpleCaseRange></SequentialCaseRange></CaseLiterals></SingleCase></SimpleCases><IntegerExpression><IntegerLiteral value="1"/></IntegerExpression></ChooseCommand></SimpleProgram>